attributes/__init__.py
attributes/core.py
attributes/examples.py
attributes-0.1.1.dist-info/LICENSE
attributes-0.1.1.dist-info/METADATA
attributes-0.1.1.dist-info/WHEEL
attributes-0.1.1.dist-info/top_level.txt
attributes-0.1.1.dist-info/RECORD
