Metadata-Version: 2.1
Name: attributes
Version: 0.1.1
Summary: UNKNOWN
Home-page: https://github.com/Cologler/attributes-python
Author: Cologler
Author-email: skyoflw@gmail.com
License: MIT License
Platform: UNKNOWN
